bootlace/__about__.py
bootlace/__init__.py
bootlace/_version.py
bootlace/breadcrumbs.py
bootlace/endpoint.py
bootlace/extension.py
bootlace/icon.py
bootlace/image.py
bootlace/links.py
bootlace/py.typed
bootlace/resources.py
bootlace/size.py
bootlace/style.py
bootlace/util.py
bootlace/forms/__init__.py
bootlace/forms/fields.py
bootlace/forms/rendering.py
bootlace/forms/templates/bootlace/_form.html
bootlace/forms/widgets/__init__.py
bootlace/forms/widgets/bootstrap.py
bootlace/forms/widgets/core.py
bootlace/forms/widgets/select.py
bootlace/forms/widgets/typed.py
bootlace/nav/__init__.py
bootlace/nav/bar.py
bootlace/nav/core.py
bootlace/nav/elements.py
bootlace/nav/nav.py
bootlace/nav/schema.py
bootlace/static/css/bootstrap-grid.css
bootlace/static/css/bootstrap-grid.css.map
bootlace/static/css/bootstrap-grid.min.css
bootlace/static/css/bootstrap-grid.min.css.map
bootlace/static/css/bootstrap-grid.rtl.css
bootlace/static/css/bootstrap-grid.rtl.css.map
bootlace/static/css/bootstrap-grid.rtl.min.css
bootlace/static/css/bootstrap-grid.rtl.min.css.map
bootlace/static/css/bootstrap-reboot.css
bootlace/static/css/bootstrap-reboot.css.map
bootlace/static/css/bootstrap-reboot.min.css
bootlace/static/css/bootstrap-reboot.min.css.map
bootlace/static/css/bootstrap-reboot.rtl.css
bootlace/static/css/bootstrap-reboot.rtl.css.map
bootlace/static/css/bootstrap-reboot.rtl.min.css
bootlace/static/css/bootstrap-reboot.rtl.min.css.map
bootlace/static/css/bootstrap-utilities.css
bootlace/static/css/bootstrap-utilities.css.map
bootlace/static/css/bootstrap-utilities.min.css
bootlace/static/css/bootstrap-utilities.min.css.map
bootlace/static/css/bootstrap-utilities.rtl.css
bootlace/static/css/bootstrap-utilities.rtl.css.map
bootlace/static/css/bootstrap-utilities.rtl.min.css
bootlace/static/css/bootstrap-utilities.rtl.min.css.map
bootlace/static/css/bootstrap.css
bootlace/static/css/bootstrap.css.map
bootlace/static/css/bootstrap.min.css
bootlace/static/css/bootstrap.min.css.map
bootlace-0.4.0.dist-info/METADATA
bootlace-0.4.0.dist-info/WHEEL
bootlace-0.4.0.dist-info/licenses/LICENSE.txt
bootlace-0.4.0.dist-info/RECORD
